{
  "users": [
    {
      "id": 1,
      "name": "admin",
      "mail": "@mail",
      "password": "admin",
      "favorites": [],
      "admin": true
    },
    {
      "name": "sulaiman",
      "mail": "sulaiman",
      "password": "sulaiman",
      "admin": false,
      "id": 2
    },
    {
      "name": "suli",
      "mail": "suli",
      "password": "suli",
      "admin": false,
      "id": 3
    },
    {
      "name": "1",
      "mail": "1",
      "password": "1",
      "admin": false,
      "id": 4
    }
  ],
  "musics": [
    {
      "name": "23456",
      "image": "2345",
      "music": "https://cdn.drivemusic.club/dl/online/uyrmkkRtYF5JhW9pNGNTvw/1697224913/download_music/2023/07/anna-asti-carica.mp3",
      "author": "234",
      "category": "13",
      "album": "123",
      "comments": [],
      "likes": [
        {
          "id": 1697292968444,
          "user": null
        },
        {
          "id": 1697440050919,
          "user": "sulaiman"
        },
        {
          "id": 1697563050678,
          "user": "suli"
        }
      ],
      "rating": [],
      "id": 1
    },
    {
      "name": "1",
      "image": "1",
      "music": "https://cdn.drivemusic.club/dl/online/uyrmkkRtYF5JhW9pNGNTvw/1697224913/download_music/2023/07/anna-asti-carica.mp3",
      "author": "1",
      "category": "1",
      "album": "1",
      "comments": [],
      "likes": [
        {
          "id": 1697296678208,
          "user": "suli"
        }
      ],
      "rating": [],
      "id": 11
    },
    {
      "name": "1",
      "image": "1",
      "music": "https://cdn.drivemusic.club/dl/online/uyrmkkRtYF5JhW9pNGNTvw/1697224913/download_music/2023/07/anna-asti-carica.mp3",
      "author": "1",
      "category": "1",
      "album": "1",
      "comments": [],
      "likes": [
        {
          "id": 1697296677447,
          "user": "suli"
        },
        {
          "id": 1697563312722,
          "user": "admin"
        }
      ],
      "rating": [],
      "id": 12
    },
    {
      "name": "Частушка",
      "image": "https://e-cdn-images.dzcdn.net/images/artist/fb0c0263e22c0f2b2790603135261a56/264x264-000000-80-0-0.jpg",
      "music": "https://cdn.drivemusic.club/dl/online/3CtRWNs5pqIqHFbz9RXlXg/1697224913/download_music/2023/10/karna.val-chastushka.mp3",
      "author": "Karna.val",
      "category": "Pop",
      "album": "НАЗВАНИЙ НЕТ - Single",
      "comments": [
        {
          "id": 1697562985422,
          "comment": "xaXA",
          "user": "admin"
        },
        {
          "id": 1697563105988,
          "comment": "xsaxsxs",
          "user": "admin"
        },
        {
          "id": 1697563134523,
          "comment": "dscvdfvv",
          "user": "suli"
        },
        {
          "id": 1697563142764,
          "comment": "xsaxasc",
          "user": "suli"
        }
      ],
      "likes": [
        {
          "id": 1697456421230,
          "user": "admin"
        }
      ],
      "rating": [],
      "id": 13
    }
  ]
}